greptimedb_mcp_server/__init__.py
greptimedb_mcp_server/config.py
greptimedb_mcp_server/formatter.py
greptimedb_mcp_server/masking.py
greptimedb_mcp_server/server.py
greptimedb_mcp_server/utils.py
greptimedb_mcp_server/templates/iot_monitoring/config.yaml
greptimedb_mcp_server/templates/iot_monitoring/template.md
greptimedb_mcp_server/templates/log_pipeline/config.yaml
greptimedb_mcp_server/templates/log_pipeline/template.md
greptimedb_mcp_server/templates/metrics_analysis/config.yaml
greptimedb_mcp_server/templates/metrics_analysis/template.md
greptimedb_mcp_server/templates/pipeline_creator/config.yaml
greptimedb_mcp_server/templates/pipeline_creator/template.md
greptimedb_mcp_server/templates/promql_analysis/config.yaml
greptimedb_mcp_server/templates/promql_analysis/template.md
greptimedb_mcp_server/templates/table_operation/config.yaml
greptimedb_mcp_server/templates/table_operation/template.md
greptimedb_mcp_server/templates/trace_analysis/config.yaml
greptimedb_mcp_server/templates/trace_analysis/template.md
greptimedb_mcp_server-0.4.4.dist-info/METADATA
greptimedb_mcp_server-0.4.4.dist-info/WHEEL
greptimedb_mcp_server-0.4.4.dist-info/entry_points.txt
greptimedb_mcp_server-0.4.4.dist-info/licenses/LICENSE.md
greptimedb_mcp_server-0.4.4.dist-info/RECORD
