Metadata-Version: 2.4
Name: greptimedb-mcp-server
Version: 0.4.4
Summary: MCP server for GreptimeDB with SQL/TQL/PromQL support, sensitive data masking, and prompt templates for observability data analysis.
Author-email: dennis zhuang <killme2008@gmail.com>
License: MIT
License-File: LICENSE.md
Requires-Python: >=3.11
Requires-Dist: aiohttp>=3.9.0
Requires-Dist: mcp>=1.8.0
Requires-Dist: mysql-connector-python>=9.1.0
Requires-Dist: pyyaml>=6.0.2
